<?xml version="1.0" ?><!DOCTYPE inventory  SYSTEM 'inventory.dtd'><inventory lemma="compromise-v">
   <commentary>
   </commentary>
   <sense group="1" n="1" name="settle by concession" type="">
      <commentary>
      </commentary>
      <examples>
        Will the union and management compromise on the contract before the deadline?
        Congress and the President must compromise on the energy bill.
        She's very hard to work with because she never compromises.
      </examples>
      <mappings>
         <wn version="3.0">1,2</wn>
         <wn lemma="" version="3.0"/>
         <omega/><pb>compromise.01</pb>
         <vn>correspond-36.1</vn><fn>NP</fn>
      </mappings><SENSE_META clarity=""/>
   </sense>
   <sense group="1" n="2" name="impair the integrity of; weaken" type="">
      <commentary>
      </commentary>
      <examples>
        She compromised her reputation by meeting with him alone.
        The illness compromised his immune system.
        The agent's secret identity has been compromised.
      </examples>
      <mappings>
         <wn version="3.0">3</wn>
         <omega/><pb>compromise.02</pb>
         <vn>NM</vn><fn>NP</fn>
      </mappings><SENSE_META clarity=""/>
   </sense>
   <WORD_META authors="brownsw,greenlm" sample_score="-"/>
</inventory>