<?xml version="1.0" ?><!DOCTYPE inventory  SYSTEM 'inventory.dtd'><inventory lemma="concentrate-v">
   <commentary>
   </commentary>
   <sense group="1" n="1" name="focus on, center upon" type="">
      <commentary>
      </commentary>
      <examples>
        Her entire attention was concentrated on her children.
        Please concentrate on your studies and not your hobbies.
        So I concentrated on the rhythmic side of things, and therefore left a lot of holes.
        You've got to concentrate bigtime.
        His reflexes were slowing as he tried to concentrate on the game.
      </examples>
      <mappings>
         <wn version="3.0">2</wn>
         <wn lemma="concentrate_on" version="3.0">1</wn>
         <omega/><pb>concentrate.01</pb>
         <vn>focus-87.1</vn><fn>NP</fn>
      </mappings><SENSE_META clarity=""/>
   </sense>
 
   <sense group="1" n="2" name="cluster or gather together, as by condensing all elements" type="">
      <commentary>
      </commentary>
      <examples>
        Because their electrons aren't as tightly concentrated, the resulting attraction is too weak.
        In the district of Krosno the occupiers concentrated the Jew population in the ghettos.
      </examples>
      <mappings>
         <wn version="3.0">3,5,6</wn>
         <wn lemma="" version=""/>
         <omega/><pb>NM</pb>
         <vn>NM</vn><fn>NP</fn>
      </mappings><SENSE_META clarity=""/>
   </sense>

   <sense group="1" n="3" name="make purer, more intense, as by removal of extraneous elements" type="">
      <commentary>
      </commentary>
      <examples>
        The cook concentrated the sauce by boiling if for a long time.
        A series of five emptied bladders concentrated the bile coming to them.
        I concentrated the sample to dryness, then dissolved in ethyl acetate.
      </examples>
      <mappings>
         <wn version="3.0">1,4,7,8</wn>
         <wn lemma="" version=""/>
         <omega/><pb>concentrate.02</pb>
         <vn>NM</vn><fn>NP</fn>
      </mappings><SENSE_META clarity=""/>
   </sense>
   <WORD_META authors="duffielc" sample_score="-"/>
</inventory>