<?xml version="1.0" ?><!DOCTYPE inventory  SYSTEM 'inventory.dtd'><inventory lemma="express-n">
    <commentary>
    </commentary>
    
    <sense group="1" n="1" name="fast public transport vehicle or line" type="">
        <commentary>
            EXPRESS[+entity][+artifact][+vehicle][+transport][+fast][+public]
        </commentary>
        <examples>
            The express run twice a day to Long Island, and the local runs hourly.
            This train is an express and only makes stops in New Haven and New York.
            We booked an overnight express with sleeping car.
        </examples>
        <mappings>
            <wn version="3.0">1</wn>
            <omega/><pb/>
        </mappings>
        <SENSE_META clarity=""/>
    </sense>
     
    
    <sense group="1" n="2" name="a rapid shipping process for goods, e.g,. mail" type="">
        <commentary>
            EXPRESS[+process][+shipping][+delivery][+rapid][+of_goods]
        </commentary>
        <examples>
            I paid to have the letters sent express.
            The package arrived by express.
        </examples>
        <mappings>
            <wn version="3.0">3,2</wn>
            <omega/><pb/>
        </mappings>
        <SENSE_META clarity=""/>
    </sense>
     
    
    <WORD_META authors="ahouston" sample_score="-"/>
</inventory>