<?xml version="1.0" ?>
<!DOCTYPE inventory SYSTEM "inventory.dtd">
<inventory lemma="grass-v">    
   <commentary>
   </commentary>
   <sense group="1" n="1" name="shoot down birds" type="">  
      <commentary>
      </commentary>
      <examples>
      A straight -away shot grassed the bird in a burst of feathers. 
      I grassed a bird he had clean missed.
      Pretty wood never grassed a bird.
      Lily-gilding on a shotgun never grassed a bird.
      The man just grassed a bird from 30 yards.
      </examples>
      <mappings>
         <gr_sense></gr_sense>
         <wn version="3.0">1</wn>   
         <wn lemma="" version="3.0"></wn>
         <omega></omega><pb>NM</pb>
         <vn>NM</vn><fn>NP</fn>
      </mappings><SENSE_META clarity=""/>
   </sense>
   <sense group="1" n="2" name="cover with grass" type="">
      <commentary>
      Includes VPC 'grass over' and 'grass in'
      </commentary>
      <examples>
      She grassed in completely her little garden in the temple. 
      The rains of the last 12 months have grassed the yard magnificently.
      We grassed the greens with TifEagle Bermuda.
      We grassed the surrounds with the same green grass to blend the transition.
      With no maid or cook to worry about, he grassed over the vegetable beds.
      He grassed over all flowerbeds, allowing his exotic peonies a natural setting. 
      </examples>
      <mappings>
         <gr_sense></gr_sense>
         <wn version="3.0">2,4</wn>
         <wn lemma="grass_over" version="3.0">1</wn>
         <omega></omega><pb>grass.01</pb>
         <vn>butter-9.9</vn><fn>NP</fn>
      </mappings><SENSE_META clarity=""/>
   </sense>
  <sense group="1" n="3" name="dry clothes on grass" type="">
      <commentary>
      </commentary>
      <examples>
      * No examples found
      </examples>
      <mappings>
         <gr_sense></gr_sense>
         <wn version="3.0">3</wn>
         <wn lemma="" version="3.0"></wn>
         <omega></omega><pb>NM</pb>
         <vn>NM</vn><fn>NP</fn>
      </mappings><SENSE_META clarity=""/>
   </sense>
  <sense group="1" n="4" name="feed with grass" type="">
      <commentary>
      </commentary>
      <examples>
      * No examples found
      </examples>
      <mappings>
         <gr_sense></gr_sense>
         <wn version="3.0">5</wn>
         <wn lemma="" version="3.0"></wn>
         <omega></omega><pb>NM</pb>
         <vn>NM</vn><fn>NP</fn>
      </mappings><SENSE_META clarity=""/>
   </sense>
  <sense group="1" n="5" name="denounce, betray, snitch on" type="">
      <commentary>
      Includes VPCs 'grass on' and 'grass up'
      </commentary>
      <examples>
      You think I should beat up this girl because she grassed on me?
      She grassed me up for benefit fraud.
      I did it out of malice as she grassed me up for pissing around.
      </examples>
      <mappings>
         <gr_sense></gr_sense>
         <wn version="3.0">6</wn>
         <wn lemma="" version="3.0"></wn>
         <omega></omega><pb>NM</pb>
         <vn>NM</vn><fn>NP</fn>
      </mappings><SENSE_META clarity=""/>
   </sense>
   <WORD_META authors="bonial" sample_score="-"/>  
</inventory>
