<?xml version="1.0" ?><!DOCTYPE inventory  SYSTEM 'inventory.dtd'><inventory lemma="infrastructure-n">
    <commentary>
        
    </commentary>
    
    <sense group="1" n="1" name="necessities" type="">
        <commentary>
            the stock of basic facilities and capital equipment needed for the
            functioning of a country or area
        </commentary>
        <examples>
            America's infrastructure relies heavily on oil.
            Infrastructure can refer to roads, bridges, and rail lines necessary for industrial economy.
        </examples>
        <mappings>
            <wn version="2.0">2</wn>
            <omega/>
            <pb/>
        </mappings>
        <SENSE_META clarity=""/>
    </sense>
    
    <sense group="1" n="2" name="substructure" type="">
        <commentary>
            the basic structure or features of a system or organization
        </commentary>
        <examples>
            The financial infrastructure the large corporation was composed of many different departments.
            Environmentalism has an infrastructure of groups, committees, and admirers.
        </examples>
        <mappings>
            <wn version="2.0">1</wn>
            <omega/>
            <pb/>
        </mappings>
        <SENSE_META clarity=""/>
    </sense>
    
    <!-- more senses go here -->
    <WORD_META authors="cstocker ajarrett" sample_score=""/>
</inventory>