<?xml version="1.0" ?>
<!DOCTYPE inventory SYSTEM "inventory.dtd">
<inventory lemma="invert-v">    
   <commentary>
   </commentary>
   <sense group="1" n="1" name="reverse the order or position of" type="">  
      <commentary>
      </commentary>
      <examples>
        Children often invert word order when learning a language.
        Musicians often invert passages to create a new effect.
        Inverting art can often lead to new perspectives on an old piece.
        Tommy inverted the letters of the alphabet due to his dyslexia.
        Bob inverted the order of the Lord of the Rings trilogy for kicks.
      </examples>
      <mappings>
         <gr_sense></gr_sense>
         <wn version="3.0">1,2</wn>   
         <wn lemma="" version="3.0"></wn>
         <omega></omega><pb>NM</pb>
         <vn>other_cos-45.4</vn><fn>NP</fn>
      </mappings><SENSE_META clarity=""/>
   </sense>
   <sense group="1" n="2" name="turn inside out or upside down" type="">
      <commentary>
      Note: May be metaphorical.
      </commentary>
      <examples>
        He has inverted the modernist dictum 'less is more'.
        Franklin inverted the hourglass to start timing the game.
        I inverted the wedding bouquet so that we could preserve the flowers.
        Nancy inverted her jeans to wash them properly.
        On April Fool's day, John inverted his clothes and wore them.
      </examples>
      <mappings>
         <gr_sense></gr_sense>
         <wn version="3.0">3</wn>
         <wn lemma="" version="3.0"></wn>
         <omega></omega><pb>invert.01</pb>
         <vn>other_cos-45.4</vn><fn>NP</fn>
      </mappings><SENSE_META clarity=""/>
   </sense>
   <WORD_META authors="donaldpl" sample_score="-"/>  
</inventory>
