<?xml version="1.0" ?><!DOCTYPE inventory  SYSTEM 'inventory.dtd'><inventory lemma="machine-n">
    <commentary>
    </commentary>
    <sense group="1" n="1" name="any device that performs work by using energy" type="">
        <commentary>
            MACHINE[+device][+physical][+performer][+work]
        </commentary>
        <examples>
            He read a great science fiction story where machines take over the world.
            They are keeping him alive on a dialysis machine.
            This machine can perform a billion instructions a second.
            That Porsche is a sweet driving machine!
            Can you use a sewing machine?
            The tiny robotic machines scrub plaque out of human arteries.
            This back hoe and the other machines on site were built in Japan.
            He runs a machine tool shop.
            In that story they used a time machine to travel back to medieval Europe.
            He wants to know why two machines on the assembly line keep breaking.
            This is a machine to make pasta.
        </examples>
        <mappings>
            <wn version="3.0">1,6,4</wn>
            <omega/><pb/>
        </mappings>
        <SENSE_META clarity=""/>
    </sense>
     
    <sense group="1" n="2" name="an organization that efficiently performs its goals" type="">
        <commentary>
            MACHINE[+organization][+efficient]
        </commentary>
        <examples>
            They needed to raise more money to feed the war machine.
            He was endorsed by Chicago's Democratic machine.
            His publication empire was a tremendous public opinion machine.
        </examples>
        <mappings>
            <wn version="3.0">3,5</wn>
            <omega/><pb/>
        </mappings>
        <SENSE_META clarity=""/>
    </sense>
     
    <sense group="1" n="3" name="a person who efficiently performs his/her goals" type="">
        <commentary>
            MACHINE[+person][+efficient]
        </commentary>
        <examples>
            Each one of those Navy Seals is a lethal fighting machine.
            The new secretary is an absolute filing machine!
        </examples>
        <mappings>
            <wn version="3.0">2</wn>
            <omega/><pb/>
        </mappings>
        <SENSE_META clarity=""/>
    </sense>
     
    <sense group="1" n="4" name="a literary device to achieve dramatic effect" type="">
        <commentary>
            MACHINE[+device][+abstract][+literary]
        </commentary>
        <examples>
            The machine of giving the protagonist amnesia is a shop-worn literary device.
            The plot machines were very predictable in that action film.
        </examples>
        <mappings>
            <wn version="Merriam-Webster online">3</wn>
            <omega/><pb/>
        </mappings>
        <SENSE_META clarity=""/>
    </sense>
     
    <WORD_META authors="ahouston" sample_score="-"/>
</inventory>