<?xml version="1.0" ?><!DOCTYPE inventory  SYSTEM 'inventory.dtd'><inventory lemma="matter-v">
   <commentary>
   </commentary>
   <sense group="1" n="1" name="have import or weight" type="">
      <commentary>
      </commentary>
      <examples>
        Does it matter what she wears as long as she comes?
        It matters to him whether she wants to have children.
        &quot;Yes! Money matters to me!&quot; she cried.
      </examples>
      <mappings>
         <wn version="3.0">1</wn>
         <wn lemma="matter_to" version="3.0">1</wn>
         <omega/><pb>matter.01</pb>
         <vn>appeal-31.4-3,matter-91</vn><fn>NP</fn>
      </mappings><SENSE_META clarity=""/>
   </sense>
   <WORD_META authors="brownsw" sample_score="-"/>
</inventory>