<?xml version="1.0" ?><!DOCTYPE inventory  SYSTEM 'inventory.dtd'><inventory lemma="outcome-n">
    <commentary>
        automatically created due to outcome.n.0 reference
    </commentary>
    
    <sense group="1" n="1" name="" type="">
        <commentary>
            OUTCOME[]
        </commentary>
        <examples>
        </examples>
        <mappings>
            <wn version="3.0"/>
            <omega/><pb/>
        </mappings>
        <SENSE_META clarity=""/>
    </sense>
     
    
    <WORD_META authors="philpot" sample_score="-"/>
</inventory>