<?xml version="1.0" ?><!DOCTYPE inventory  SYSTEM 'inventory.dtd'><inventory lemma="point-n">
    <commentary>
        
    </commentary>
    
    
    <sense group="1" n="1" name="dot" type="">
        <commentary>
            a geometric element of a very small circular shape that has position
            but no extension
        </commentary>
        <examples>
            They sailed south around the point.
        </examples>
        <mappings>
            <wn version="2.0">1 9 17</wn>
            <omega/>
            <pb/>
        </mappings>
        <SENSE_META clarity=""/>
    </sense>
    
    <sense group="1" n="2" name="location" type="">
        <commentary>
            spot - 
            the precise location of something; a spatially limited location
        </commentary>
        <examples>
            She walked to a point where she could survey the whole street.
        </examples>
        <mappings>
            <wn version="2.0">2</wn>
            <omega/>
            <pb/>
        </mappings>
        <SENSE_META clarity=""/>
    </sense>
    
    <sense group="1" n="3" name="meaning" type="">
        <commentary>
            the essential meaning/purpose or idea of an activity
        </commentary>
        <examples>
            Get to the point.
            He missed the point of the joke.
            Life has lost its point.
            What is the point of discussing it?
        </examples>
        <mappings>
            <wn version="2.0">3 7</wn>
            <omega/>
            <pb/>
        </mappings>
        <SENSE_META clarity=""/>
    </sense>
    
    <sense group="1" n="4" name="detail" type="">
        <commentary>
            bullet, item - 
            a distinct part that can be specified separately in a group of things
            which could be enumerated on a list
        </commentary>
        <examples>
            Several of the points are similar.
            The third point of information in Eric's presentation was false.
            The amount of money being wasted was the point that got my attention.
            He knows my bad points as well as my good points.
            He noticed a point in the New York Times.
            His acting was one of the high points of the movie.
        </examples>
        <mappings>
            <wn version="2.0">5 12 13 14 21</wn>
            <omega/>
            <pb/>
        </mappings>
        <SENSE_META clarity=""/>
    </sense>
    
    <sense group="1" n="5" name="degree, level, stage" type="">
        <commentary>
            degree, level, stage - 
            a specific identifiable position in a continuum or series or
            especially in a process (as in a point in time, or a point along a
            line)
        </commentary>
        <examples>
            At that point I had to leave his office.
            At some point during the train ride the lights had gone out.
            We must've started traveling north at some point.
        </examples>
        <mappings>
            <wn version="2.0">4 6</wn>
            <omega/>
            <pb/>
        </mappings>
        <SENSE_META clarity=""/>
    </sense>
    
    <sense group="1" n="6" name="sharp tip" type="">
        <commentary>
            peak - 
            a &quot;V&quot; shape or sharp end
        </commentary>
        <examples>
            The cannibal's teeth were filed to a sharp points.
            He stuck the point of the knife into a tree.
            He broke the point of his pencil.
            The point of the arrow was due north
        </examples>
        <mappings>
            <wn version="2.0">8 15 19 20</wn>
            <omega/>
            <pb/>
        </mappings>
        <SENSE_META clarity=""/>
    </sense>
    
    <sense group="1" n="7" name="game scoring" type="">
        <commentary>
            the unit of counting in scoring a game or contest
        </commentary>
        <examples>
            He scored 20 points in the first half.
            A touchdown counts 6 points.
        </examples>
        <mappings>
            <wn version="2.0">10</wn>
            <omega/>
            <pb/>
        </mappings>
        <SENSE_META clarity=""/>
    </sense>
    
    <sense group="1" n="8" name="cape" type="">
        <commentary>
            peninsula - 
            a promontory extending out into a large body of water
        </commentary>
        <examples>
            They sailed south around the point.
            The kids favorite surfing spot is just around the point.
        </examples>
        <mappings>
            <wn version="2.0">11</wn>
            <omega/>
            <pb/>
        </mappings>
        <SENSE_META clarity=""/>
    </sense>
    
    <sense group="1" n="9" name="punctuation mark" type="">
        <commentary>
            full stop, stop, full point -  
            a punctuation mark (.) placed at the end of a declarative sentence to
            indicate a full stop or after abbreviation
        </commentary>
        <examples>
            In England they call a point a stop.
        </examples>
        <mappings>
            <wn version="2.0">18</wn>
            <omega/>
            <pb/>
        </mappings>
        <SENSE_META clarity=""/>
    </sense>
    
    <sense group="1" n="10" name="point" type="Compass">
        <commentary>
            any of 32 horizontal directions indicated on the card of a compass
        </commentary>
        <examples>
            He checked the point on his compass.
        </examples>
        <mappings>
            <wn version="2.0">16</wn>
            <omega/>
            <pb/>
        </mappings>
        <SENSE_META clarity=""/>
    </sense>
    
    <sense group="1" n="11" name="gunpoint" type="">
        <commentary>
            the gun muzzle's direction
        </commentary>
        <examples>
            He held me up at the point of a gun.
        </examples>
        <mappings>
            <wn version="2.0">22</wn>
            <omega/>
            <pb/>
        </mappings>
        <SENSE_META clarity=""/>
    </sense>
    
    <sense group="1" n="12" name="wall socket" type="">
        <commentary>
            a power point; a wall socket; electrical socket
        </commentary>
        <examples>
            This apartment has four power points in each room.
            She uses one of those air fresheners that plug into a power point.
        </examples>
        <mappings>
            <wn version="2.0">23</wn>
            <omega/>
            <pb/>
        </mappings>
        <SENSE_META clarity=""/>
    </sense>
    
    <sense group="1" n="13" name="breaker point" type="">
        <commentary>
            distributor point - 
            a contact in the distributor; as the rotor turns its projecting arm
            contacts distributor points and current flows to the spark plugs
        </commentary>
        <examples>
            Adjusting breaker points is the most complex aspect of engine tune-ups.
        </examples>
        <mappings>
            <wn version="2.0">24</wn>
            <omega/>
            <pb/>
        </mappings>
        <SENSE_META clarity=""/>
    </sense>
    
    <sense group="1" n="14" name="fraction" type="Financial">
        <commentary>
            stock point
        </commentary>
        <examples>
            Microsoft went up 3 points today.
            The DOW fell 16 points yesterday but recovered nicely today.
        </examples>
        <mappings>
            <wn version="2.0">-</wn>
            <omega/>
            <pb/>
        </mappings>
        <SENSE_META clarity=""/>
    </sense>
    
    <!-- catherine proposes that we have a collective sense for various idioms -->
    <WORD_META authors="cstocker ajarrett" sample_score=""/>
</inventory>