<?xml version="1.0" ?>
<!DOCTYPE inventory SYSTEM "inventory.dtd">
<inventory lemma="sympathize-v">    
   <commentary>
   </commentary>
   <sense group="1" n="1" name="agree with" type="">  
      <commentary>
      </commentary>
      <examples>
      One can only sympathize with him in his new position. 
      I sympathize with this stance. 
      And initially the jurors did sympathize with Hans. 
      </examples>
      <mappings>
         <gr_sense></gr_sense>
         <wn version="3.0">1</wn>   
         <wn lemma="" version="3.0"></wn>
         <omega></omega><pb>sympathize.01</pb>
         <vn>NM</vn><fn>NM</fn>
      </mappings><SENSE_META clarity=""/>
   </sense>
   <sense group="1" n="2" name="relate to and empathize with" type="">
      <commentary>
      </commentary>
      <examples>
      And I think he is going to do more than just sympathize. 
      "I can sympathize," Billy said. 
      I sympathize with her role and what her goal is. 
      She was a character so easy to sympathize with, empathize with.
      I sympathize with your predicament. 
      You can sympathize with yoru kid's disappointment and still be firm. 
      I'm sure any new HDTV owner will sympathize. 
      </examples>
      <mappings>
         <gr_sense></gr_sense>
         <wn version="3.0">2,3</wn>
         <wn lemma="" version="3.0"></wn>
         <omega></omega><pb>sympathize.01</pb>
         <vn>empathize-88.2</vn><fn>Emotion_directed</fn>
      </mappings><SENSE_META clarity=""/>
   </sense>
   <WORD_META authors="congerk" sample_score="-"/>  
</inventory>
