<?xml version="1.0" ?><!DOCTYPE inventory  SYSTEM 'inventory.dtd'><inventory lemma="warn-v">
   <commentary>
   </commentary>
   <sense group="1" n="1" name="make someone aware or counsel someone of possible danger or problem" type="">
      <commentary>
      </commentary>
      <examples>
        The director warned him that he might be fired.
        The doctor warned him of the dangers of smoking, as it can cause cancer.
        I warned you that I would ask some difficult questions.
        Hey, I warned ya' it was long.
        I warned him not to go too far.
        I warned you against false assumptions.
        The old man warned the children off his property.
        She warned him not to take any action because whatever he did, he would regret it!
      </examples>
      <mappings>
         <wn version="3.0">1,2,3,4</wn>
         <wn lemma="" version=""/>
         <omega/><pb>warn.01</pb>
         <vn>advise-37.9</vn>
      </mappings><SENSE_META clarity=""/>
   </sense>
   <WORD_META authors="duffielc,vieweg,hwangd" sample_score="-"/>
</inventory>